{
    "id": "cover-beeindruckende-websites",
    "html": "\n<section class=\"cover-beeindruckende-websites-section\" data-ai-id=\"element-placeholder\">\n    <div class=\"container\">\n        <h1 class=\"anim-fade-in-up\">{{t:title}}</h1>\n        <p class=\"subtitle anim-fade-in-up anim-delay-1\">{{t:subtitle}}</p>\n        <a href=\"#\" class=\"btn btn-dark anim-fade-in-up anim-delay-2\">{{t:cta_button}}</a>\n        <div class=\"video-placeholder-wrapper anim-zoom-in anim-delay-3\">\n            <div class=\"video-placeholder-inner\"><img src=\"https://pixabay.com/api/?key=52494880-f6ccd6f4c90db08ed73d4f14d&q=faq+website+interface\" alt=\"{{t:image_alt}}\"></div>\n        </div>\n        <div class=\"logo-wall anim-fade-in-up anim-delay-4\">\n            <img src=\"https://logo.clearbit.com/insidebrief.com\" alt=\"Logo\"><img src=\"https://logo.clearbit.com/moderndigest.com\" alt=\"Logo\"><img src=\"https://logo.clearbit.com/nextfoundry.com\" alt=\"Logo\"><img src=\"https://logo.clearbit.com/thefrankfurter.com\" alt=\"Logo\"><img src=\"https://logo.clearbit.com/thereviewer.com\" alt=\"Logo\">\n        </div>\n    </div>\n</section>",
    "css": ".cover-beeindruckende-websites-section { padding: 6rem 0; } .container { max-width: 900px; margin: 0 auto; text-align: center; } h1 { font-size: clamp(2.5rem, 5vw, 3.5rem); margin-bottom: 1rem; } .subtitle { max-width: 500px; margin: 0 auto 2rem; } .btn-dark { display: inline-block; padding: 0.8rem 2rem; background-color: var(--color-dark); color: var(--color-light); border-radius: 0.5rem; text-decoration: none; margin-bottom: 4rem; } .video-placeholder-wrapper { background-color: var(--color-dark); padding: 1.5rem; border-radius: 1.5rem; box-shadow: 0 10px 30px rgba(0,0,0,0.1); } .video-placeholder-inner { border-radius: 1rem; overflow: hidden; } .video-placeholder-inner img { width: 100%; display: block; } .logo-wall { display: flex; justify-content: space-around; align-items: center; flex-wrap: wrap; gap: 2rem; margin-top: 4rem; filter: grayscale(100%) opacity(0.7); } .logo-wall img { height: 24px; }",
    "translations": {
        "de": { "name": "Beeindruckende Websites", "title": "Erstelle in Minuten beeindruckende Websites", "subtitle": "Du kannst ein .gif als Vorschau für dein Video hochladen.", "cta_button": "Aktion", "image_alt": "Website-Interface" },
        "en": { "name": "Impressive Websites", "title": "Create impressive websites in minutes", "subtitle": "You can upload a .gif as a preview for your video.", "cta_button": "Action", "image_alt": "Website interface" },
        "ar": { "name": "مواقع رائعة", "title": "أنشئ مواقع رائعة في دقائق", "subtitle": "يمكنك تحميل ملف .gif كمعاينة للفيديو الخاص بك.", "cta_button": "إجراء", "image_alt": "واجهة الموقع" }
    }
}