{
    "name": "Nav with Auth Buttons (Light)",
    "category": "Menu",
    "description": "A light-themed, professional navigation bar with user authentication buttons ('Sign In' and 'Sign Up'). Well-suited for web applications, membership sites, and online platforms.",
    "tags": ["authentication", "auth-buttons", "light-theme", "web-app", "saas", "header", "responsive"],
    "structure": ["logo", "nav-links", "auth-buttons"],
    "complexity": "medium",
    "use_cases": [
        "Web Applications",
        "Membership Sites",
        "Online Courses",
        "SaaS Platforms"
    ]
}
