{
    "id": "products-modern-card-hover-zoom",
    "html": "<section class=\"modern-product-cards\">\n  <h2>New Arrivals</h2>\n  <div class=\"product-card-wrapper\">\n    <div class=\"product-card-modern\">\n      <div class=\"img-container\">\n        <img src=\"https://pixabay.com/api/?key=52494880-f6ccd6f4c90db08ed73d4f14d&q=modern+minimalist+vase&image_type=photo\" alt=\"Product 1\">\n      </div>\n      <div class=\"card-info\">\n        <h4>Minimalist Vase</h4>\n        <p>Elegant ceramic vase with a smooth matte finish.</p>\n        <div class=\"price\">$55.00</div>\n        <a href=\"#\" class=\"shop-link\">Shop Now</a>\n      </div>\n    </div>\n    <div class=\"product-card-modern\">\n      <div class=\"img-container\">\n        <img src=\"https://pixabay.com/api/?key=52494880-f6ccd6f4c90db08ed73d4f14d&q=modern+geometric+clock&image_type=photo\" alt=\"Product 2\">\n      </div>\n      <div class=\"card-info\">\n        <h4>Geometric Clock</h4>\n        <p>A unique timepiece that blends art and function.</p>\n        <div class=\"price\">$90.00</div>\n        <a href=\"#\" class=\"shop-link\">Shop Now</a>\n      </div>\n    </div>\n    <div class=\"product-card-modern\">\n      <div class=\"img-container\">\n        <img src=\"https://pixabay.com/api/?key=52494880-f6ccd6f4c90db08ed73d4f14d&q=modern+desk+organizer+wood&image_type=photo\" alt=\"Product 3\">\n      </div>\n      <div class=\"card-info\">\n        <h4>Wooden Organizer</h4>\n        <p>Keep your workspace tidy with this stylish organizer.</p>\n        <div class=\"price\">$40.00</div>\n        <a href=\"#\" class=\"shop-link\">Shop Now</a>\n      </div>\n    </div>\n    <div class=\"product-card-modern\">\n      <div class=\"img-container\">\n        <img src=\"https://pixabay.com/api/?key=52494880-f6ccd6f4c90db08ed73d4f14d&q=modern+throw+blanket+neutral&image_type=photo\" alt=\"Product 4\">\n      </div>\n      <div class=\"card-info\">\n        <h4>Neutral Throw Blanket</h4>\n        <p>Cozy and chic, perfect for any season.</p>\n        <div class=\"price\">$70.00</div>\n        <a href=\"#\" class=\"shop-link\">Shop Now</a>\n      </div>\n    </div>\n  </div>\n</section>",
    "css": ".modern-product-cards {\n  padding: 60px 20px;\n  background-color: #f8f9fa;\n  font-family: 'Poppins', sans-serif;\n}\n\n.modern-product-cards h2 {\n  text-align: center;\n  font-size: 2.8em;\n  color: #343a40;\n  margin-bottom: 40px;\n  font-weight: 700;\n}\n\n.product-card-wrapper {\n  display: grid;\n  grid-template-columns: 1fr;\n  gap: 30px;\n  max-width: 1100px;\n  margin: 0 auto;\n}\n\n.product-card-modern {\n  background-color: #ffffff;\n  border-radius: 15px;\n  overflow: hidden;\n  box-shadow: 0 8px 20px rgba(0, 0, 0, 0.1);\n  transition: transform 0.4s cubic-bezier(0.25, 0.8, 0.25, 1), box-shadow 0.4s cubic-bezier(0.25, 0.8, 0.25, 1);\n  display: flex;\n  flex-direction: column;\n}\n\n.img-container {\n  width: 100%;\n  height: 280px;\n  overflow: hidden;\n  position: relative;\n}\n\n.img-container img {\n  width: 100%;\n  height: 100%;\n  object-fit: cover;\n  display: block;\n  transition: transform 0.5s cubic-bezier(0.25, 0.8, 0.25, 1);\n}\n\n.product-card-modern:hover {\n  transform: translateY(-12px);\n  box-shadow: 0 18px 35px rgba(0, 0, 0, 0.15);\n}\n\n.product-card-modern:hover .img-container img {\n  transform: scale(1.08);\n}\n\n.card-info {\n  padding: 25px;\n  text-align: center;\n  flex-grow: 1;\n  display: flex;\n  flex-direction: column;\n  justify-content: space-between;\n}\n\n.card-info h4 {\n  font-size: 1.5em;\n  color: #343a40;\n  margin-bottom: 10px;\n  font-weight: 700;\n}\n\n.card-info p {\n  font-size: 0.95em;\n  color: #6c757d;\n  line-height: 1.6;\n  margin-bottom: 15px;\n}\n\n.card-info .price {\n  font-size: 1.3em;\n  font-weight: bold;\n  color: #dc3545;\n  margin-bottom: 20px;\n}\n\n.shop-link {\n  display: inline-block;\n  background-color: #007bff;\n  color: #ffffff;\n  padding: 12px 30px;\n  border-radius: 30px;\n  text-decoration: none;\n  font-weight: 600;\n  font-size: 0.95em;\n  transition: background-color 0.3s ease, transform 0.3s ease;\n}\n\n.shop-link:hover {\n  background-color: #0056b3;\n  transform: translateY(-2px);\n}\n\n@media (min-width: 768px) {\n  .product-card-wrapper {\n    grid-template-columns: repeat(2, 1fr);\n  }\n}\n\n@media (min-width: 1024px) {\n  .product-card-wrapper {\n    grid-template-columns: repeat(4, 1fr);\n  }\n}\n",
    "js": "document.addEventListener('DOMContentLoaded', function() {\n    const images = document.querySelectorAll('img[src^=\"https://pixabay.com/api/\"]');\n    images.forEach(img => {\n        fetch(img.src)\n            .then(response => response.json())\n            .then(data => {\n                if (data.hits && data.hits.length > 0) {\n                    img.src = data.hits[0].largeImageURL;\n                } else {\n                    img.src = 'https://via.placeholder.com/1280x720?text=Image+Not+Found';\n                }\n            })\n            .catch(error => {\n                console.error('Error fetching Pixabay image:', error);\n                img.src = 'https://via.placeholder.com/1280x720?text=Image+Not+Found';\n            });\n    });\n});",
    "translations": {
        "de": {
            "name": "Produkte Moderne Karte Hover Zoom"
        },
        "ar": {
            "name": "بطاقات منتجات عصرية مع تكبير عند التحويم"
        },
        "en": {
            "name": "Products Modern Card Hover Zoom"
        }
    }
}